{
  "id": "塊",
  "kanjialiveData": null,
  "jishoData": {
    "query": "塊",
    "found": true,
    "taughtIn": "junior high",
    "jlptLevel": "N1",
    "newspaperFrequencyRank": "1800",
    "strokeCount": 13,
    "meaning": {
      "en": "clod, lump, chunk, clot, mass",
      "vi": "cục, khối, mảng, đám"
    },
    "kunyomi": [
      "かたまり",
      "つちくれ"
    ],
    "onyomi": [
      "カイ",
      "ケ"
    ],
    "onyomiExamples": [
      {
        "example": "塊茎",
        "reading": "カイケイ",
        "meaning": {
          "en": "tuber",
          "vi": "củ"
        },
        "romaji": "kaikei"
      },
      {
        "example": "塊鉱",
        "reading": "カイコウ",
        "meaning": {
          "vi": "lump ore",
          "en": "lump ore"
        },
        "romaji": "kaikou"
      },
      {
        "example": "団塊",
        "reading": "ダンカイ",
        "meaning": {
          "vi": "mass, lump, clod, clump, nodule, baby boom generation (of 1947-1949), babyboomer (born between 1947-1949)",
          "en": "mass, lump, clod, clump, nodule, baby boom generation (of 1947-1949), babyboomer (born between 1947-1949)"
        },
        "romaji": "dankai"
      },
      {
        "example": "山塊",
        "reading": "サンカイ",
        "meaning": {
          "en": "mountain mass, massif",
          "vi": "khối núi"
        },
        "romaji": "sankai"
      }
    ],
    "kunyomiExamples": [
      {
        "example": "塊",
        "reading": "かたまり",
        "meaning": {
          "vi": "lump, mass, bundle, clump, clod, cluster, group, crowd, embodiment (of an idea, quality, feeling etc.), personification",
          "en": "lump, mass, bundle, clump, clod, cluster, group, crowd, embodiment (of an idea, quality, feeling etc.), personification"
        },
        "romaji": "katamari"
      },
      {
        "example": "塊魂",
        "reading": "かたまりだましい",
        "meaning": {
          "en": "Katamari Damacy (2004 video game)",
          "vi": "Katamari Damacy, trò chơi điện tử năm 2004"
        },
        "romaji": "katamaridamashii"
      },
      {
        "example": "一塊",
        "reading": "いっかい",
        "meaning": {
          "vi": "one lump, one group",
          "en": "one lump, one group"
        },
        "romaji": "ikkai"
      },
      {
        "example": "拝金主義の塊",
        "reading": "はいきんしゅぎのかたまり",
        "meaning": {
          "vi": "money-worshiper",
          "en": "money-worshiper"
        },
        "romaji": "haikinshuginokatamari"
      }
    ],
    "radical": {
      "symbol": "土",
      "meaning": {
        "en": "earth",
        "vi": "đất"
      }
    },
    "parts": [
      "儿",
      "匕",
      "厶",
      "土",
      "田",
      "鬼"
    ],
    "strokeOrderDiagramUri": "http://classic.jisho.org/static/images/stroke_diagrams/22602_frames.png",
    "strokeOrderSvgUri": "https://d1w6u4xc3l95km.cloudfront.net/kanji-2015-03/0584a.svg",
    "strokeOrderGifUri": "https://raw.githubusercontent.com/mistval/kanji_images/master/gifs/584a.gif",
    "uri": "https://jisho.org/search/%E5%A1%8A%23kanji"
  },
  "jlpt": "N1",
  "mnemonic_vi": "Gợi ý cách nhớ: 土 là đất, 鬼 như một khối gồ lên kỳ quặc, nhìn như cục đất vón lại.",
  "hanViet": [
    "khối"
  ]
}
